eds/__init__.py
eds/core.py
eds/exceptions.py
EDS_Lib-1.1.1.dist-info/LICENSE
EDS_Lib-1.1.1.dist-info/METADATA
EDS_Lib-1.1.1.dist-info/WHEEL
EDS_Lib-1.1.1.dist-info/top_level.txt
EDS_Lib-1.1.1.dist-info/RECORD
