Metadata-Version: 2.1
Name: EDS-Lib
Version: 1.1.1
Summary: Encoded Data Storages Lib on Python
Home-page: https://github.com/mk-samoilov/EDS-Python-Lib
Author: mk-samoilov
Author-email: maksim.samoilov.0202@gmail.com
Classifier: Programming Language :: Python :: 3
Classifier: License :: OSI Approved :: MIT License
Classifier: Operating System :: OS Independent
Requires-Python: >=2.0
License-File: LICENSE
